{
  "source": "openexchangerates",
  "base": "USD",
  "date": "2026-04-29",
  "rates": {
    "AED": 3.6731,
    "AFN": 62.999998,
    "ALL": 81.712674,
    "AMD": 369.651974,
    "ANG": 1.79,
    "AOA": 918,
    "ARS": 1393.507,
    "AUD": 1.402702,
    "AWG": 1.8025,
    "AZN": 1.7,
    "BAM": 1.670824,
    "BBD": 2,
    "BDT": 122.736122,
    "BGN": 1.672209,
    "BHD": 0.377539,
    "BIF": 2976,
    "BMD": 1,
    "BND": 1.277332,
    "BOB": 6.912076,
    "BRL": 5.015359,
    "BSD": 1,
    "BTC": 0.000013182708,
    "BTN": 94.471981,
    "BWP": 13.520821,
    "BYN": 2.816686,
    "BZD": 2.011858,
    "CAD": 1.367293,
    "CDF": 2320,
    "CHF": 0.790246,
    "CLF": 0.02288,
    "CLP": 900.71,
    "CNH": 6.843149,
    "CNY": 6.8383,
    "COP": 3623.37,
    "CRC": 454.910503,
    "CUC": 1,
    "CUP": 25.75,
    "CVE": 94.4,
    "CZK": 20.85714,
    "DJF": 177.5,
    "DKK": 6.391081,
    "DOP": 59.25,
    "DZD": 132.502015,
    "EGP": 52.997799,
    "ERN": 15,
    "ETB": 157.375,
    "EUR": 0.855083,
    "FJD": 2.2066,
    "FKP": 0.74132,
    "GBP": 0.74132,
    "GEL": 2.695,
    "GGP": 0.74132,
    "GHS": 11.14,
    "GIP": 0.74132,
    "GMD": 73.500003,
    "GNF": 8777.5,
    "GTQ": 7.642463,
    "GYD": 209.283579,
    "HKD": 7.836823,
    "HNL": 26.62,
    "HRK": 6.441898,
    "HTG": 131.014207,
    "HUF": 312.521905,
    "IDR": 17371.966335,
    "ILS": 2.9724,
    "IMP": 0.74132,
    "INR": 94.813051,
    "IQD": 1310.482947,
    "IRR": 1315500,
    "ISK": 122.96,
    "JEP": 0.74132,
    "JMD": 157.527267,
    "JOD": 0.709,
    "JPY": 160.23525,
    "KES": 129.1,
    "KGS": 87.4293,
    "KHR": 4010,
    "KMF": 421.000027,
    "KPW": 900,
    "KRW": 1487.609215,
    "KWD": 0.307902,
    "KYD": 0.833615,
    "KZT": 463.324935,
    "LAK": 21945,
    "LBP": 89600,
    "LKR": 318.68567,
    "LRD": 183.749993,
    "LSL": 16.588385,
    "LYD": 6.345,
    "MAD": 9.25625,
    "MDL": 17.216242,
    "MGA": 4149,
    "MKD": 52.729964,
    "MMK": 2099.81,
    "MNT": 3569.47,
    "MOP": 8.075024,
    "MRU": 40,
    "MUR": 46.829999,
    "MVR": 15.45,
    "MWK": 1734.560684,
    "MXN": 17.495022,
    "MYR": 3.9525,
    "MZN": 63.909994,
    "NAD": 16.55,
    "NGN": 1372.42,
    "NIO": 36.811438,
    "NOK": 9.295267,
    "NPR": 151.155304,
    "NZD": 1.713605,
    "OMR": 0.384505,
    "PAB": 1,
    "PEN": 3.514643,
    "PGK": 4.34475,
    "PHP": 61.724008,
    "PKR": 278.725,
    "PLN": 3.643117,
    "PYG": 6267.211067,
    "QAR": 3.64325,
    "RON": 4.3634,
    "RSD": 100.407015,
    "RUB": 74.745224,
    "RWF": 1460.5,
    "SAR": 3.75069,
    "SBD": 8.025935,
    "SCR": 13.530462,
    "SDG": 600.5,
    "SEK": 9.298912,
    "SGD": 1.280454,
    "SHP": 0.74132,
    "SLE": 24.625,
    "SLL": 20969.5,
    "SOS": 571.690154,
    "SRD": 37.465,
    "SSP": 130.26,
    "STD": 22281.8,
    "STN": 21.25,
    "SVC": 8.753075,
    "SYP": 13002,
    "SZL": 16.55,
    "THB": 32.7615,
    "TJS": 9.37795,
    "TMT": 3.505,
    "TND": 2.88375,
    "TOP": 2.40776,
    "TRY": 45.070099,
    "TTD": 6.801873,
    "TWD": 31.639002,
    "TZS": 2595,
    "UAH": 44.090006,
    "UGX": 3726.439291,
    "USD": 1,
    "UYU": 39.886654,
    "UZS": 12070,
    "VES": 484.61877,
    "VND": 26356,
    "VUV": 119.389,
    "WST": 2.74422,
    "XAF": 560.897667,
    "XAG": 0.01397995,
    "XAU": 0.00021988,
    "XCD": 2.70255,
    "XCG": 1.802812,
    "XDR": 0.697718,
    "XOF": 560.897667,
    "XPD": 0.00068913,
    "XPF": 102.038542,
    "XPT": 0.00052333,
    "YER": 238.649953,
    "ZAR": 16.772364,
    "ZMW": 18.880707,
    "ZWG": 25.3626,
    "ZWL": 322
  },
  "fetchedAt": 1777480874968
}