{
  "source": "openexchangerates",
  "base": "USD",
  "date": "2026-04-01",
  "rates": {
    "AED": 3.6725,
    "AFN": 63.999997,
    "ALL": 82.659229,
    "AMD": 376.663831,
    "ANG": 1.79,
    "AOA": 912.13,
    "ARS": 1382.50595,
    "AUD": 1.437918,
    "AWG": 1.80125,
    "AZN": 1.7,
    "BAM": 1.70594,
    "BBD": 2,
    "BDT": 122.977226,
    "BGN": 1.685099,
    "BHD": 0.377515,
    "BIF": 2970.665588,
    "BMD": 1,
    "BND": 1.28264,
    "BOB": 6.908351,
    "BRL": 5.1793,
    "BSD": 1,
    "BTC": 0.000014558375,
    "BTN": 92.792367,
    "BWP": 13.788472,
    "BYN": 2.973319,
    "BZD": 2.010774,
    "CAD": 1.389163,
    "CDF": 2314.479428,
    "CHF": 0.791754,
    "CLF": 0.023392,
    "CLP": 923.53,
    "CNH": 6.874365,
    "CNY": 6.8744,
    "COP": 3672.453617,
    "CRC": 464.839655,
    "CUC": 1,
    "CUP": 25.75,
    "CVE": 96.057187,
    "CZK": 21.11585,
    "DJF": 178.03978,
    "DKK": 6.43745,
    "DOP": 59.897169,
    "DZD": 132.721673,
    "EGP": 53.628538,
    "ERN": 15,
    "ETB": 156.112359,
    "EUR": 0.861508,
    "FJD": 2.2574,
    "FKP": 0.750666,
    "GBP": 0.750666,
    "GEL": 2.69,
    "GGP": 0.750666,
    "GHS": 10.998199,
    "GIP": 0.750666,
    "GMD": 74.000005,
    "GNF": 8767.951552,
    "GTQ": 7.648319,
    "GYD": 209.250218,
    "HKD": 7.837325,
    "HNL": 26.5591,
    "HRK": 6.491537,
    "HTG": 131.237699,
    "HUF": 329.20021,
    "IDR": 16929.18105,
    "ILS": 3.13074,
    "IMP": 0.750666,
    "INR": 93.396498,
    "IQD": 1309.68375,
    "IRR": 1315875,
    "ISK": 123.88,
    "JEP": 0.750666,
    "JMD": 158.120389,
    "JOD": 0.709,
    "JPY": 158.34841667,
    "KES": 130.07,
    "KGS": 87.45,
    "KHR": 4000.241379,
    "KMF": 428.499999,
    "KPW": 900,
    "KRW": 1504.885147,
    "KWD": 0.309093,
    "KYD": 0.833229,
    "KZT": 475.291699,
    "LAK": 22035.07603,
    "LBP": 89549.014385,
    "LKR": 315.172115,
    "LRD": 183.462125,
    "LSL": 17.146882,
    "LYD": 6.377046,
    "MAD": 9.33924,
    "MDL": 17.611846,
    "MGA": 4179.583365,
    "MKD": 53.107908,
    "MMK": 2099.81,
    "MNT": 3569.47,
    "MOP": 8.072575,
    "MRU": 39.88606,
    "MUR": 46.79,
    "MVR": 15.47,
    "MWK": 1733.677062,
    "MXN": 17.861601,
    "MYR": 4.027,
    "MZN": 63.950001,
    "NAD": 17.146882,
    "NGN": 1381.88,
    "NIO": 36.794904,
    "NOK": 9.654919,
    "NPR": 152.178238,
    "NZD": 1.732022,
    "OMR": 0.384497,
    "PAB": 1,
    "PEN": 3.478665,
    "PGK": 4.323975,
    "PHP": 60.179994,
    "PKR": 278.954625,
    "PLN": 3.6872,
    "PYG": 6493.339553,
    "QAR": 3.645288,
    "RON": 4.391,
    "RSD": 101.137695,
    "RUB": 80.303086,
    "RWF": 1463.214886,
    "SAR": 3.753374,
    "SBD": 8.042037,
    "SCR": 13.866522,
    "SDG": 601,
    "SEK": 9.378318,
    "SGD": 1.281715,
    "SHP": 0.750666,
    "SLE": 24.55,
    "SLL": 20969.5,
    "SOS": 571.374608,
    "SRD": 37.374,
    "SSP": 130.26,
    "STD": 22281.8,
    "STN": 21.117322,
    "SVC": 8.748077,
    "SYP": 13002,
    "SZL": 17.141088,
    "THB": 32.4925,
    "TJS": 9.560589,
    "TMT": 3.51,
    "TND": 2.934847,
    "TOP": 2.40776,
    "TRY": 44.474384,
    "TTD": 6.785987,
    "TWD": 31.967001,
    "TZS": 2595,
    "UAH": 43.749677,
    "UGX": 3724.311264,
    "USD": 1,
    "UYU": 40.63762,
    "UZS": 12144.423745,
    "VES": 473.278079,
    "VND": 26336.581512,
    "VUV": 119.389,
    "WST": 2.74422,
    "XAF": 565.112363,
    "XAG": 0.01330321,
    "XAU": 0.00021038,
    "XCD": 2.70255,
    "XCG": 1.801759,
    "XDR": 0.710952,
    "XOF": 565.112363,
    "XPD": 0.00067593,
    "XPF": 102.80528,
    "XPT": 0.00050867,
    "YER": 238.649953,
    "ZAR": 16.79175,
    "ZMW": 19.270981,
    "ZWG": 25.3626,
    "ZWL": 322
  },
  "fetchedAt": 1775046854395
}